{
  "title": "台股 KD 低檔站上 5MA 放量篩選",
  "updated": "2026-07-04 03:00 Asia/Taipei",
  "latest_date": "2026-07-02",
  "rules": "K<30、D<30；收盤由下往上站上5MA；成交量 > 前5日均量2倍",
  "sources": [
    "TWSE OpenAPI",
    "TPEX OpenAPI",
    "Yahoo chart API"
  ],
  "universe_count": 1971,
  "error_count": 0,
  "matches": [
    {
      "code": "6641",
      "name": "基士德-KY",
      "market": "上市",
      "date": "2026-07-02",
      "close": 18.15,
      "change_pct": 0.83,
      "K": 17.7,
      "D": 16.4,
      "ma5": 18.01,
      "prev_close": 18.0,
      "prev_ma5": 18.01,
      "volume": 520000,
      "vol_avg5_prev": 39200,
      "vol_ratio": 13.27,
      "ma5_turn_up": false
    },
    {
      "code": "5438",
      "name": "東友",
      "market": "上櫃",
      "date": "2026-07-02",
      "close": 19.1,
      "change_pct": 4.09,
      "K": 27.1,
      "D": 27.6,
      "ma5": 18.66,
      "prev_close": 18.35,
      "prev_ma5": 18.71,
      "volume": 628395,
      "vol_avg5_prev": 114438,
      "vol_ratio": 5.49,
      "ma5_turn_up": false
    },
    {
      "code": "8083",
      "name": "瑞穎",
      "market": "上櫃",
      "date": "2026-07-02",
      "close": 171.0,
      "change_pct": 0.29,
      "K": 22.7,
      "D": 29.0,
      "ma5": 170.7,
      "prev_close": 170.5,
      "prev_ma5": 171.0,
      "volume": 136120,
      "vol_avg5_prev": 32425,
      "vol_ratio": 4.2,
      "ma5_turn_up": false
    },
    {
      "code": "1294",
      "name": "漢田生技",
      "market": "上櫃",
      "date": "2026-07-02",
      "close": 66.25,
      "change_pct": 0.89,
      "K": 25.4,
      "D": 26.3,
      "ma5": 65.77,
      "prev_close": 65.67,
      "prev_ma5": 65.78,
      "volume": 581014,
      "vol_avg5_prev": 142138,
      "vol_ratio": 4.09,
      "ma5_turn_up": false
    },
    {
      "code": "6146",
      "name": "耕興",
      "market": "上櫃",
      "date": "2026-07-02",
      "close": 192.0,
      "change_pct": 0.52,
      "K": 27.7,
      "D": 23.9,
      "ma5": 191.1,
      "prev_close": 191.0,
      "prev_ma5": 191.8,
      "volume": 1090336,
      "vol_avg5_prev": 278438,
      "vol_ratio": 3.92,
      "ma5_turn_up": false
    }
  ]
}